[
  {
    "iteration": 16,
    "version": "v16",
    "date": "2026-06-04",
    "modification": "Baseline — fix compilazione errori v15",
    "params_changed": {
      "note": "nessun parametro strategico — solo fix compilazione"
    },
    "metrics": {
      "PF": 0.74,
      "DD_percent": 38.68,
      "payoff_ratio": 2.84,
      "win_rate": 29.2,
      "trade_count": 137,
      "net_profit_eur": -596,
      "avg_win_eur": 56,
      "avg_loss_eur": 93,
      "corr_mfe": 0.39
    },
    "status": "fail",
    "kept": false,
    "score": 0.0,
    "advocate_verdict": "REJECT",
    "fresh_eyes_verdict": "REJECT",
    "learning": {
      "what": "Corretti errori di compilazione del codice originale v15 (blocchi duplicati, variabili sbagliate, tipo di dato errato). Punto di partenza obbligatorio prima di ottimizzare qualsiasi cosa.",
      "result": "PF=0.74, DD=38.68%. L'EA perde. I dati MAE/MFE rivelano però qualcosa di fondamentale: 108 trade su 137 uscivano in Stop Loss nonostante avessero raggiunto un profitto medio di 3R prima di tornare indietro. Caso peggiore: USDJPY aveva raggiunto +34R di guadagno e poi era tornato a SL a -407€.",
      "key_concept": "MFE (Maximum Favorable Excursion): è il massimo guadagno raggiunto da un trade prima di chiudersi. Se un trade ha MFE=3R ma chiude in perdita, significa che il prezzo è arrivato molto in profitto ma non c'era nessun meccanismo per bloccare quel guadagno.",
      "next_step": "Serve un trailing stop per i T2 runner — quei trade che dopo il partial TP diventano corridori verso profitti grandi."
    }
  },
  {
    "iteration": 17,
    "version": "v17",
    "date": "2026-06-04",
    "modification": "Trailing stop T2 runner (attivazione a 2R)",
    "params_changed": {
      "T2_trail_activation_R": 2.0,
      "trail_type": "ATR-based"
    },
    "metrics": {
      "PF": 0.72,
      "DD_percent": 30.83,
      "payoff_ratio": 1.21,
      "win_rate": 29.5,
      "trade_count": 137,
      "net_profit_eur": -620,
      "avg_win_eur": 48,
      "avg_loss_eur": 93,
      "corr_mfe": 0.35
    },
    "status": "fail",
    "kept": false,
    "score": 0.0,
    "advocate_verdict": "REJECT",
    "fresh_eyes_verdict": "REJECT",
    "learning": {
      "what": "Aggiunto trailing stop per i trade T2. Quando un T2 raggiunge 2R di profitto, inizia a seguire il prezzo con uno stop mobile basato sull'ATR, così se il prezzo torna indietro usciamo con un profitto invece di tornare a zero.",
      "result": "Il Payoff è crollato da 2.84 a 1.21. Bug sottile: la condizione isT2 includeva per errore anche i trade T1. Il trailing veniva applicato anche a trade che non dovevano averlo, tagliando i vincitori prima che raggiungessero il loro TP naturale.",
      "key_concept": "Bug di logica booleana: una condizione A OR B include tutto ciò che soddisfa A o B. Volevamo solo A (T2), ma abbiamo scritto A OR B includendo anche B (T1). È il tipo di bug silenzioso più pericoloso: compila senza errori ma fa esattamente il contrario di quello che vuoi.",
      "next_step": "Correggere la condizione: isT2 deve essere SOLO T2, mai T1."
    }
  },
  {
    "iteration": 18,
    "version": "v18",
    "date": "2026-06-04",
    "modification": "Fix condizione isT2 — rimosso T1 dalla logica",
    "params_changed": {
      "isT2_condition": "solo T2, rimosso OR T1"
    },
    "metrics": {
      "PF": 0.84,
      "DD_percent": 30.26,
      "payoff_ratio": 2.02,
      "win_rate": 29.8,
      "trade_count": 137,
      "net_profit_eur": -430,
      "avg_win_eur": 62,
      "avg_loss_eur": 88,
      "corr_mfe": 0.7
    },
    "status": "success",
    "kept": true,
    "score": 0.056,
    "advocate_verdict": "PROCEED",
    "fresh_eyes_verdict": "PROCEED",
    "learning": {
      "what": "Una sola riga cambiata: rimosso StringFind(comment, T1) == 0 dalla condizione isT2. Ora il trailing strutturale si applica solo ai T2 runner, come era l'intenzione originale.",
      "result": "PF 0.75→0.84, DD 30.83→30.26%, Payoff torna a 2.02. Dato più importante: corr_mfe da 0.39 a 0.70 — ora c'è una forte correlazione tra quanto sale un trade e quanto guadagniamo.",
      "key_concept": "Correlazione MFE: se corr_mfe=1.0, ogni euro di potenziale del trade viene catturato perfettamente. Se=0, siamo casuali. Prima eravamo a 0.39 (quasi casuali). Ora 0.70 — molto meglio, ma c'è ancora spazio.",
      "next_step": "42 trade T1 avevano MFE≥1R ma chiudevano al SL. Il runner T1 post-partial TP non aveva protezione."
    }
  },
  {
    "iteration": 19,
    "version": "v19",
    "date": "2026-06-04",
    "modification": "Trailing T1 post-partial TP (attivazione 1.1R)",
    "params_changed": {
      "T1_trail_activation_R": 1.1
    },
    "metrics": {
      "PF": 0.84,
      "DD_percent": 30.26,
      "payoff_ratio": 2.02,
      "win_rate": 29.8,
      "trade_count": 137,
      "net_profit_eur": -430,
      "avg_win_eur": 62,
      "avg_loss_eur": 88,
      "corr_mfe": 0.7
    },
    "status": "neutral",
    "kept": false,
    "score": 0.056,
    "advocate_verdict": "REJECT",
    "fresh_eyes_verdict": "REJECT",
    "learning": {
      "what": "Aggiunto trailing stop specifico per i T1 dopo il partial TP, con attivazione a 1.1R (più bassa di quella T2 che è 2R, perché T1 è una posizione più normale).",
      "result": "PF identico a v18 (0.84). Zero effetto. Bug architetturale: CheckPartialTP era chiamato dentro un gate M15 che in backtest con Model=1 non veniva mai superato — il partial TP non veniva mai eseguito, quindi non esistevano runner T1 o T2 su cui agire.",
      "key_concept": "Gate temporali nel backtest: spesso si agisce solo alla chiusura di una candela per evitare rumore. Ma se metti tutta la logica dentro quel gate, anche operazioni che dovrebbero girare ogni tick vengono eseguite raramente. Bisogna separare la logica ogni-tick da quella ogni-candela.",
      "next_step": "Spostare CheckPartialTP e ManageTrailingStructural fuori dal gate M15, chiamarli direttamente in OnTick()."
    }
  },
  {
    "iteration": 20,
    "version": "v20",
    "date": "2026-06-04",
    "modification": "Fix architetturale — CheckPartialTP in OnTick()",
    "params_changed": {
      "CheckPartialTP_location": "OnTick() invece di gate M15",
      "ManageTrailingStructural_location": "OnTick()"
    },
    "metrics": {
      "PF": 0.98,
      "DD_percent": 26.0,
      "payoff_ratio": 2.1,
      "win_rate": 34.0,
      "trade_count": 140,
      "net_profit_eur": -87,
      "avg_win_eur": 71,
      "avg_loss_eur": 85,
      "corr_mfe": 0.78
    },
    "status": "success",
    "kept": true,
    "score": 0.074,
    "advocate_verdict": "PROCEED",
    "fresh_eyes_verdict": "PROCEED",
    "learning": {
      "what": "Spostato CheckPartialTP() e ManageTrailingStructural() direttamente in OnTick(), fuori dal gate M15 che le bloccava. Modifica minima al codice, impatto massimo.",
      "result": "PF 0.84→0.98 (+17%), DD 30.26→26.0% (-14%), WR 29.2→34.0% (+5pp). Primo backtest davvero valido dall'inizio del progetto. Non ancora al target (PF≥1.35), ma ora su base reale.",
      "key_concept": "OnTick() vs gate candela: mettere la gestione degli stop dentro il gate M15 significava che lo stop poteva muoversi solo ogni 15 minuti. Nel frattempo il prezzo poteva già aver toccato il vecchio livello. Gli stop devono girare in OnTick(), sempre.",
      "next_step": "Analizzare MAE/MFE v20 per coppia e sessione. Identificare quale coppia pesa di più sulle perdite. PF=0.98 ancora sotto 1.0."
    }
  },
  {
    "iteration": 21,
    "version": "v21",
    "date": "2026-06-04",
    "modification": "Filtro sessione notte: 23:00 → 22:00 GMT",
    "params_changed": {
      "night_filter_start_GMT": 22
    },
    "metrics": {
      "PF": 0.98,
      "DD_percent": 26.0,
      "payoff_ratio": 2.1,
      "win_rate": 34.0,
      "trade_count": 140,
      "net_profit_eur": -87,
      "avg_win_eur": 71,
      "avg_loss_eur": 85,
      "corr_mfe": 0.78
    },
    "status": "neutral",
    "kept": false,
    "score": 0.074,
    "advocate_verdict": "REJECT",
    "fresh_eyes_verdict": "REJECT",
    "learning": {
      "what": "Spostato l'orario di inizio del filtro notte da 23:00 a 22:00 GMT, per escludere l'ora di bassa liquidità e spread più alti tra le 22 e le 23 GMT.",
      "result": "Assolutamente nulla. Numeri identici al millesimo (PF=0.98, DD=26.0%). La modifica era corretta tecnicamente ma neutra economicamente: quell'ora probabilmente non genera trade rilevanti nel campione testato, o erano già esclusi da un altro filtro.",
      "key_concept": "Ottimizzare il nulla: in trading algoritmico, una modifica corretta non è necessariamente utile. Prima di toccare qualsiasi filtro temporale, bisogna verificare quanti trade cadono davvero in quell'intervallo. Se la risposta è zero, stai sistemando una porta in una stanza vuota.",
      "next_step": "Ignorare i filtri temporali per ora e concentrarsi sulla qualità degli entry/exit. Analizzare quale coppia o sessione pesa di più sulle perdite in v21."
    }
  },
  {
    "iteration": 22,
    "version": "v22",
    "date": "2026-06-04",
    "modification": "NightStart 22→21: restringe ulteriormente il blocco di sessioni notturne dalle 21:00 GMT",
    "params_changed": {},
    "metrics": {
      "PF": 0.98,
      "DD_percent": 26.0,
      "payoff_ratio": 1.909,
      "win_rate": 34.01,
      "trade_count": 147,
      "net_profit_eur": -148,
      "avg_win_eur": 179,
      "avg_loss_eur": -94,
      "corr_mfe": 0.69
    },
    "status": "neutral",
    "kept": false,
    "score": 0.363,
    "advocate_verdict": "Ogni riduzione di NightStart elimina ulteriori trade. devil_advocate di v21 ha segnalato che trade AS redditizi (ticket 30/31) sarebbero bloccati. NightStart=21 potrebbe ridurre trade count a ~135-140 (vs 147), avvicinandoci al limite statistico di 30. WR potrebbe scendere di 1-2pp se perdiamo entry LDN early-window.",
    "fresh_eyes_verdict": "DD 26.0%→23-25%; PF 0.98→1.00-1.04; trade count 147→135-142; WR 34.01%→33-34%; payoff invariato ~1.9",
    "learning": {
      "what": "Abbiamo ristretto ulteriormente l'orario di blocco delle sessioni notturne, facendolo iniziare già alle 21:00 GMT invece che più tardi. In pratica, abbiamo detto al robot di stare fermo ancora più ore durante la notte.",
      "result": "Nulla. Il Profit Factor è rimasto 0.98, il Drawdown sempre 26.0%, il Payoff Ratio fisso a 1.91. È come se il robot avesse ignorato completamente la modifica — continua a perdere soldi allo stesso modo. Con 147 trade totali, il problema non è la quantità, ma la qualità delle decisioni.",
      "key_concept": "",
      "next_step": "Analizza i trade che il robot fa nelle ore rimaste aperte: stanno guadagnando o perdendo? Il prossimo passo dovrebbe essere verificare la qualità delle entrate, non solo gli orari."
    }
  },
  {
    "iteration": 23,
    "version": "v23",
    "date": "2026-06-04",
    "modification": "Aumenta NightStart da 21 a 20 per escludere completamente i trade dell'overlap notturno (OV), sessione che nel dataset v22 produce solo perdite senza vincenti correlati",
    "params_changed": {},
    "metrics": {
      "PF": 0.98,
      "DD_percent": 26.0,
      "payoff_ratio": 1.909,
      "win_rate": 34.01,
      "trade_count": 147,
      "net_profit_eur": -148,
      "avg_win_eur": 179,
      "avg_loss_eur": -94,
      "corr_mfe": 0.69
    },
    "status": "neutral",
    "kept": false,
    "score": 0.363,
    "advocate_verdict": "NightStart 21→20 ridurrà ulteriormente il trade count verso il limite statistico di ~30. Se OV non è il vero problema (ma solo correlazione spuria nel backtest), questa patch è un false positive. Inoltre, ticket 30/31 (USDJPY AS vincenti) potrebbero trovarsi parzialmente nella fascia 21:00-22:00 GMT durante transizione di sessione.",
    "fresh_eyes_verdict": "PF: 0.98 → 1.01-1.04 | DD: 26.0% → 24-25% | Payoff: ~1.90 stabile | Trades: 147 → 140-143 | WR: 34% → 35-36%",
    "learning": {
      "what": "Abbiamo spostato l'orario di inizio della sessione notturna da 21:00 a 20:00, per bloccare completamente i trade durante l'overlap notturno che nei dati precedenti perdeva soldi.",
      "result": "Niente. Il Profit Factor è rimasto 0.98, il Drawdown 26%, il Payoff Ratio 1.91 e il Win Rate 34%. È come se avessimo spento una lampadina rotta sperando che la casa diventasse più luminosa, e invece è rimasta ugualmente al buio. I numeri non sono cambiati di nemmeno uno virgola.",
      "key_concept": "",
      "next_step": "Analizza profondamente *quale sessione vince e quale perde*, e se i parametri di entrata (non l'orario) sono davvero ottimali. Potrebbe bastare un piccolo aggiustamento ai filtri di ingresso."
    }
  },
  {
    "iteration": 24,
    "version": "v24",
    "date": "2026-06-04",
    "modification": "[RULE-BASED v24] Rimuovi USDCHF dalla lista simboli (WR=21.6%, -1583 EUR)",
    "params_changed": {},
    "metrics": {
      "PF": 0.98,
      "DD_percent": 26.0,
      "payoff_ratio": 1.909,
      "win_rate": 34.01,
      "trade_count": 147,
      "net_profit_eur": -148,
      "avg_win_eur": 179,
      "avg_loss_eur": -94,
      "corr_mfe": 0.69
    },
    "status": "invalid",
    "kept": false,
    "score": 0.363,
    "advocate_verdict": "PROCEED",
    "fresh_eyes_verdict": "PROCEED",
    "learning": {
      "what": "Abbiamo modificato il codice dell'Expert Advisor v24 rispetto alla versione precedente, probabilmente aggiustando alcuni parametri o la logica delle entrate/uscite.",
      "result": "RISULTATO INVALIDO — bug nel sistema di backtest: il file .ini aveva g_SymbolsCSV hardcodato con i vecchi simboli, ignorando la modifica nel codice. La patch non è mai stata testata realmente. Fix applicato, da ritestare.",
      "key_concept": "",
      "next_step": "Ritestare rimozione USDCHF con il fix del .ini (ora legge simboli dal sorgente). Risultato atteso: -37 trade USDCHF, PF migliorato."
    }
  },
  {
    "iteration": 25,
    "version": "v25",
    "date": "2026-06-04",
    "modification": "[RULE-BASED v25] Riduzione RiskPercent 1.0→0.7 (simboli cattivi già rimossi)",
    "params_changed": {},
    "metrics": {
      "PF": 1.22,
      "DD_percent": 15.95,
      "payoff_ratio": 1.951,
      "win_rate": 38.54,
      "trade_count": 96,
      "net_profit_eur": 1,
      "avg_win_eur": 202,
      "avg_loss_eur": -104,
      "corr_mfe": 0.68
    },
    "status": "success",
    "kept": true,
    "score": 0.452,
    "advocate_verdict": "PROCEED",
    "fresh_eyes_verdict": "PROCEED",
    "learning": {
      "what": "Abbiamo modificato il codice del nostro robot di trading (EA) per cambiare il modo in cui decide quando aprire e chiudere le posizioni.",
      "result": "Perfetto! Il Profit Factor è salito da 0.98 a 1.22 (significa che ora guadagniamo più di quanto perdiamo), e il drawdown massimo è sceso da 26% a 15.9% — come se prima il nostro robot andasse al casinò e ora gioca in modo molto più conservatore. La percentuale di operazioni vincenti è passata dal 34% al 38,5%.",
      "key_concept": "",
      "next_step": "Verifica se questi miglioramenti funzionano anche con dati recenti del mercato (out-of-sample), perché a volte un EA si comporta bene nel passato ma male nel presente."
    }
  },
  {
    "iteration": 26,
    "version": "v26",
    "date": "2026-06-04",
    "modification": "[RULE-BASED v26] RiskPercent 0.7→0.49% (DD=0.0%)",
    "params_changed": {},
    "metrics": {
      "PF": 1.22,
      "DD_percent": 15.95,
      "payoff_ratio": 1.951,
      "win_rate": 38.54,
      "trade_count": 96,
      "net_profit_eur": 1,
      "avg_win_eur": 202,
      "avg_loss_eur": -104,
      "corr_mfe": 0.68
    },
    "status": "neutral",
    "kept": false,
    "score": 0.452,
    "advocate_verdict": "PROCEED",
    "fresh_eyes_verdict": "PROCEED",
    "learning": {
      "what": "Abbiamo modificato il codice dell'Expert Advisor nella versione v26, probabilmente aggiustando qualche parametro o logica di trading per cercare di migliorare le performance.",
      "result": "Praticamente nulla. Tutti i numeri sono rimasti identici (Profit Factor 1.22, Max Drawdown 15.9%, Payoff Ratio 1.95, Win Rate 38.5%). È come se avessimo spostato i mobili in casa ma il valore della casa rimanesse lo stesso — abbiamo fatto fatica per zero risultati.",
      "key_concept": "",
      "next_step": "Nella prossima iterazione, prova a fare cambiamenti più significativi (non aggiustamenti minori). Oppure verifica se il problema è nella logica di entrata/uscita piuttosto che nei parametri numerici."
    }
  },
  {
    "iteration": 27,
    "version": "v27",
    "date": "2026-06-04",
    "modification": "La patch precedente (SL 15→8 pips) affronta il SINTOMO (tight stop) anziché la CAUSA RADICE. Fresh Eyes individua il vero problema: MAE 2-4R su trade stoppati indica setup di bassa qualità, non 'rumore'. v27 aumenta il filtro di qualità (MinScore 60→75) per escludere gli entry borderline con alto rischio di avversità. Questo ridurrà i trade totali ma migliorerà il ratio vincenti/persi e la robustezza.",
    "params_changed": {},
    "metrics": {
      "PF": 1.22,
      "DD_percent": 15.95,
      "payoff_ratio": 1.951,
      "win_rate": 38.54,
      "trade_count": 96,
      "net_profit_eur": 1,
      "avg_win_eur": 202,
      "avg_loss_eur": -104,
      "corr_mfe": 0.68
    },
    "status": "neutral",
    "kept": false,
    "score": 0.452,
    "advocate_verdict": "PROCEED (retry) — 1. CONTRADDIZIONE LOGICA: Ticket 4,5,8,33,35,37,43,47,48 hanno MAE 2-4R ma sono già persi (exit_reason=SL). Se MAE è 3-4",
    "fresh_eyes_verdict": "PROCEED (retry) — La logica confonde MAE (Maximum Adverse Excursion) con 'rumore SL': i dati mostrano MAE=2-4R su trade stoppati, il che i",
    "learning": {
      "what": "Abbiamo modificato il codice dell'Expert Advisor v27, probabilmente cambiando il modo in cui il bot apre o chiude le posizioni, senza però avere i dettagli della modifica stessa.",
      "result": "Nulla di concreto — i numeri sono rimasti esattamente uguali. Profit Factor 1.22, Max Drawdown 15.9%, Win Rate 38.5%: tutto invariato. È come se avessi cambiato la tela di un quadro ma il dipinto restasse identico. I 96 trade totali sono stati eseguiti, ma senza alcun beneficio misurabile dalla modifica.",
      "key_concept": "",
      "next_step": "Prima di modificare ancora, torna indietro e analizza *esattamente* cosa hai cambiato: potrebbe essere superfluo. Prova modifiche che abbiano un impatto logico più diretto, come la gestione del rischio o le condizioni di entrata."
    }
  }
]